{
  "$schema": "https://schema.management.azure.com/schemas/2019-04-01/deploymentTemplate.json#",
  "contentVersion": "1.0.0.0",
  "parameters": {
    "location": {
      "type": "string",
      "defaultValue": "northeurope"
    },
    "vmName": {
      "type": "string",
      "defaultValue": "vm-az104-d2-01"
    },
    "adminUsername": {
      "type": "string",
      "defaultValue": "azureuser"
    },
    "adminPublicKey": {
      "type": "string"
    },
    "vmSize": {
      "type": "string",
      "defaultValue": "Standard_B1s"
    },
    "vnetName": {
      "type": "string",
      "defaultValue": "vnet-az104-d2-01"
    },
    "subnetName": {
      "type": "string",
      "defaultValue": "snet-default"
    },
    "nsgName": {
      "type": "string",
      "defaultValue": "nsg-az104-d2-01"
    },
    "publicIpName": {
      "type": "string",
      "defaultValue": "pip-az104-d2-01"
    },
    "nicName": {
      "type": "string",
      "defaultValue": "nic-az104-d2-01"
    }
  },
  "resources": [
    {
      "type": "Microsoft.Network/networkSecurityGroups",
      "apiVersion": "2023-11-01",
      "name": "[parameters('nsgName')]",
      "location": "[parameters('location')]",
      "properties": {
        "securityRules": [
          {
            "name": "allow-ssh",
            "properties": {
              "priority": 100,
              "access": "Allow",
              "direction": "Inbound",
              "protocol": "Tcp",
              "sourcePortRange": "*",
              "destinationPortRange": "22",
              "sourceAddressPrefix": "*",
              "destinationAddressPrefix": "*"
            }
          }
        ]
      }
    },
    {
      "type": "Microsoft.Network/virtualNetworks",
      "apiVersion": "2023-11-01",
      "name": "[parameters('vnetName')]",
      "location": "[parameters('location')]",
      "properties": {
        "addressSpace": {
          "addressPrefixes": [
            "10.30.0.0/16"
          ]
        },
        "subnets": [
          {
            "name": "[parameters('subnetName')]",
            "properties": {
              "addressPrefix": "10.30.1.0/24",
              "networkSecurityGroup": {
                "id": "[resourceId('Microsoft.Network/networkSecurityGroups', parameters('nsgName'))]"
              }
            }
          }
        ]
      },
      "dependsOn": [
        "[resourceId('Microsoft.Network/networkSecurityGroups', parameters('nsgName'))]"
      ]
    },
    {
      "type": "Microsoft.Network/publicIPAddresses",
      "apiVersion": "2023-11-01",
      "name": "[parameters('publicIpName')]",
      "location": "[parameters('location')]",
      "sku": {
        "name": "Standard"
      },
      "properties": {
        "publicIPAllocationMethod": "Static"
      }
    },
    {
      "type": "Microsoft.Network/networkInterfaces",
      "apiVersion": "2023-11-01",
      "name": "[parameters('nicName')]",
      "location": "[parameters('location')]",
      "dependsOn": [
        "[resourceId('Microsoft.Network/virtualNetworks', parameters('vnetName'))]",
        "[resourceId('Microsoft.Network/publicIPAddresses', parameters('publicIpName'))]"
      ],
      "properties": {
        "ipConfigurations": [
          {
            "name": "ipconfig1",
            "properties": {
              "subnet": {
                "id": "[resourceId('Microsoft.Network/virtualNetworks/subnets', parameters('vnetName'), parameters('subnetName'))]"
              },
              "privateIPAllocationMethod": "Dynamic",
              "publicIPAddress": {
                "id": "[resourceId('Microsoft.Network/publicIPAddresses', parameters('publicIpName'))]"
              }
            }
          }
        ]
      }
    },
    {
      "type": "Microsoft.Compute/virtualMachines",
      "apiVersion": "2023-09-01",
      "name": "[parameters('vmName')]",
      "location": "[parameters('location')]",
      "dependsOn": [
        "[resourceId('Microsoft.Network/networkInterfaces', parameters('nicName'))]"
      ],
      "properties": {
        "hardwareProfile": {
          "vmSize": "[parameters('vmSize')]"
        },
        "osProfile": {
          "computerName": "[parameters('vmName')]",
          "adminUsername": "[parameters('adminUsername')]",
          "linuxConfiguration": {
            "disablePasswordAuthentication": true,
            "ssh": {
              "publicKeys": [
                {
                  "path": "[format('/home/{0}/.ssh/authorized_keys', parameters('adminUsername'))]",
                  "keyData": "[parameters('adminPublicKey')]"
                }
              ]
            }
          }
        },
        "storageProfile": {
          "imageReference": {
            "publisher": "Canonical",
            "offer": "0001-com-ubuntu-server-jammy",
            "sku": "22_04-lts-gen2",
            "version": "latest"
          },
          "osDisk": {
            "createOption": "FromImage",
            "managedDisk": {
              "storageAccountType": "Standard_LRS"
            }
          }
        },
        "networkProfile": {
          "networkInterfaces": [
            {
              "id": "[resourceId('Microsoft.Network/networkInterfaces', parameters('nicName'))]",
              "properties": {
                "primary": true
              }
            }
          ]
        }
      }
    }
  ],
  "outputs": {
    "scenario": {
      "type": "string",
      "value": "day2-scenario01"
    },
    "deployedVmName": {
      "type": "string",
      "value": "[parameters('vmName')]"
    },
    "publicIpAddress": {
      "type": "string",
      "value": "[reference(resourceId('Microsoft.Network/publicIPAddresses', parameters('publicIpName')), '2023-11-01').ipAddress]"
    }
  }
}
